cfn_pyplates-0.5.1.dist-info/DESCRIPTION.rst
cfn_pyplates-0.5.1.dist-info/WHEEL
cfn_pyplates-0.5.1.dist-info/pbr.json
cfn_pyplates-0.5.1.dist-info/METADATA
cfn_pyplates-0.5.1.dist-info/RECORD
cfn_pyplates-0.5.1.dist-info/top_level.txt
cfn_pyplates-0.5.1.dist-info/metadata.json
cfn_pyplates-0.5.1.dist-info/entry_points.txt
cfn_pyplates/cli.py
cfn_pyplates/exceptions.py
cfn_pyplates/core.py
cfn_pyplates/options.py
cfn_pyplates/__init__.py
cfn_pyplates/functions.py
