Metadata-Version: 2.0
Name: cfn-pyplates
Version: 0.5.1
Summary: Amazon Web Services CloudFormation template generator
Home-page: UNKNOWN
Author: Sean Myers
Author-email: sean.dst@gmail.com
License: MIT
Keywords: setup
Requires-Dist: setuptools
Requires-Dist: docopt
Requires-Dist: ordereddict
Requires-Dist: pbr
Requires-Dist: pyyaml
Requires-Dist: schema
